pepperoni/__init__.py
pepperoni/cache.py
pepperoni/credentials.py
pepperoni/database.py
pepperoni/formatter.py
pepperoni/header.py
pepperoni/logger.py
pepperoni/output.py
pepperoni/record.py
pepperoni/sysinfo.py
pepperoni/utils.py
pepperoni-0.2.1.dist-info/LICENSE
pepperoni-0.2.1.dist-info/METADATA
pepperoni-0.2.1.dist-info/WHEEL
pepperoni-0.2.1.dist-info/top_level.txt
pepperoni-0.2.1.dist-info/RECORD
