Metadata-Version: 2.1
Name: pepperoni
Version: 0.2.1
Summary: Developer-friendly Python toolkit.
Home-page: https://github.com/t3eHawk/pepperoni
Author: Timur Faradzhov
Author-email: timurfaradzhov@gmail.com
License: MIT
Platform: UNKNOWN
Classifier: Programming Language :: Python :: 3
Classifier: License :: OSI Approved :: MIT License
Classifier: Operating System :: OS Independent
Requires-Dist: sqlalchemy (>=1.3.1)
